pymeu/__init__.py
pymeu/cfutility.py
pymeu/comms.py
pymeu/meutility.py
pymeu/cf/__init__.py
pymeu/cf/dmk.py
pymeu/cf/messages.py
pymeu/cf/types.py
pymeu/cf/validation.py
pymeu/common/__init__.py
pymeu/common/messages.py
pymeu/common/types.py
pymeu/common/validation.py
pymeu/me/__init__.py
pymeu/me/application.py
pymeu/me/decompress.py
pymeu/me/enums.py
pymeu/me/firmware.py
pymeu/me/fuwhelper.py
pymeu/me/helper.py
pymeu/me/messages.py
pymeu/me/primitives.py
pymeu/me/registry.py
pymeu/me/transfer.py
pymeu/me/types.py
pymeu/me/util.py
pymeu/me/validation.py
pymeu-0.4.10.dist-info/licenses/LICENSE
pymeu-0.4.10.dist-info/METADATA
pymeu-0.4.10.dist-info/WHEEL
pymeu-0.4.10.dist-info/top_level.txt
pymeu-0.4.10.dist-info/RECORD
