Metadata-Version: 2.4
Name: pymeu
Version: 0.4.10
Summary: Python ME Utility
Author-email: aawilliams85 <adair.williams85@gmail.com>
License: MIT License
Project-URL: Repository, https://github.com/aawilliams85/pymeu.git
License-File: LICENSE
Requires-Dist: olefile>=0.47
Provides-Extra: pycomm3
Requires-Dist: pycomm3>=1.2.14; extra == "pycomm3"
Provides-Extra: pylogix
Requires-Dist: pylogix>=1.1.2; extra == "pylogix"
Dynamic: license-file
